wth/__init__.py
wth/log.py
wth/data/__init__.py
wth/data/seq_data_helper.py
wth/notification/__init__.py
wth/notification/base.py
wth/notification/dingtalk.py
wth/notification/wechat.py
wth/torch/utils/__init__.py
wth/torch/utils/data.py
wth/utils/__init__.py
wth/utils/cache.py
wth/utils/config.py
wth/utils/dataclass.py
wth/utils/get_time.py
wth/utils/progress.py
wth/utils/reflect.py
wth/utils/stopwatch.py
wttch_train_helper-0.0.39.dist-info/LICENSE
wttch_train_helper-0.0.39.dist-info/METADATA
wttch_train_helper-0.0.39.dist-info/WHEEL
wttch_train_helper-0.0.39.dist-info/top_level.txt
wttch_train_helper-0.0.39.dist-info/RECORD
