Metadata-Version: 2.1
Name: wttch-train-helper
Version: 0.0.39
Summary: Wttch's train helper
Author: wttch
Author-email: Wttch <wttch@wttch.com>
Project-URL: Homepage, https://github.com/wttch96/train-helper
Project-URL: Issues, https://github.com/wttch96/train-helper/issues
Classifier: Programming Language :: Python :: 3
Classifier: License :: OSI Approved :: MIT License
Classifier: Operating System :: OS Independent
Requires: torch
Requires: numpy
Requires: prettytable
Requires-Python: >=3.8
License-File: LICENSE
